[{"year":2017,"value":599449},{"year":2016,"value":582014},{"year":2015,"value":569604},{"year":2014,"value":556319},{"year":2013,"value":543360},{"year":2012,"value":530946},{"year":2011,"value":518347},{"year":2010,"value":506953},{"year":2009,"value":497783},{"year":2008,"value":488650},{"year":2007,"value":479993},{"year":2006,"value":472637},{"year":2005,"value":465158},{"year":2004,"value":458095},{"year":2003,"value":451630},{"year":2002,"value":446175},{"year":2001,"value":441525},{"year":2000,"value":436300},{"year":1999,"value":430475},{"year":1998,"value":424700},{"year":1997,"value":419450},{"year":1996,"value":414225},{"year":1995,"value":408625},{"year":1994,"value":402925},{"year":1993,"value":397475},{"year":1992,"value":392175},{"year":1991,"value":387000},{"year":1990,"value":381850},{"year":1989,"value":377100},{"year":1988,"value":373450},{"year":1987,"value":370750},{"year":1986,"value":368355},{"year":1985,"value":366706},{"year":1984,"value":365998},{"year":1983,"value":365622},{"year":1982,"value":365525},{"year":1981,"value":365225},{"year":1980,"value":364150},{"year":1979,"value":362856},{"year":1978,"value":362007},{"year":1977,"value":361358},{"year":1976,"value":360731},{"year":1975,"value":358950},{"year":1974,"value":355050},{"year":1973,"value":350450},{"year":1972,"value":346600},{"year":1971,"value":342421},{"year":1970,"value":339171},{"year":1969,"value":337500},{"year":1968,"value":335850},{"year":1967,"value":334995},{"year":1966,"value":333895},{"year":1965,"value":331500},{"year":1964,"value":327750},{"year":1963,"value":324100},{"year":1962,"value":320750},{"year":1961,"value":316845},{"year":1960,"value":313970}]