[{"year":1973,"value":20.39},{"year":1974,"value":21.22},{"year":1975,"value":20.98},{"year":1976,"value":21.74},{"year":1977,"value":20.9},{"year":1978,"value":20.95},{"year":1979,"value":20.56},{"year":1980,"value":19.9},{"year":1981,"value":20.83},{"year":1982,"value":22.58},{"year":1983,"value":21.48},{"year":1984,"value":22.65},{"year":1985,"value":22.77},{"year":1986,"value":24.81},{"year":1987,"value":24.2},{"year":1988,"value":25.48},{"year":1989,"value":25.22},{"year":1990,"value":25.32},{"year":1991,"value":26.08},{"year":1992,"value":27.26},{"year":1993,"value":28.3},{"year":1994,"value":29.51},{"year":1995,"value":29.42},{"year":1996,"value":30.28},{"year":1997,"value":30.41},{"year":1998,"value":30.29},{"year":1999,"value":29.23},{"year":2000,"value":28.17},{"year":2001,"value":26.81},{"year":2002,"value":28.25},{"year":2003,"value":29.9},{"year":2004,"value":29.14},{"year":2005,"value":30.21},{"year":2006,"value":30.07},{"year":2007,"value":31.14},{"year":2008,"value":32.91},{"year":2009,"value":31.67},{"year":2010,"value":33.01},{"year":2011,"value":31.94},{"year":2012,"value":34.96},{"year":2013,"value":36.77},{"year":2014,"value":36.69},{"year":2015,"value":36.1},{"year":2016,"value":33.77}]